README.md
setup.py
PersistenceImages/__init__.py
PersistenceImages/cdfs.py
PersistenceImages/persistence_images.py
PersistenceImages/weighting_fxns.py
PersistenceImages.egg-info/PKG-INFO
PersistenceImages.egg-info/SOURCES.txt
PersistenceImages.egg-info/dependency_links.txt
PersistenceImages.egg-info/top_level.txt