Metadata-Version: 1.1
Name: PersistenceImages
Version: 1.3.1
Summary: Functions to vectorize persistence diagrams into persistence images (see [PI] http://www.jmlr.org/papers/volume18/16-337/16-337.pdf for details)
Home-page: https://gitlab.com/csu-tda/PersistenceImages
Author: Francis C. Motta
Author-email: fmotta@fau.edu
License: MIT
Keywords: persistence diagrams,persistent homology,persistence images,computational topology,topological data analysis
Platform: UNKNOWN
Classifier: Development Status :: 4 - Beta
